.travis.yml
AUTHORS
ChangeLog
LICENSE
README.md
desktop.ini
requirements.txt
setup.cfg
setup.py
tox.ini
chat/__init__.py
chat/api.py
chat/apilib.py
chat/app.py
chat/client.py
chat/config.py
chat/graph.py
chat/ianswer.py
chat/kmapi.py
chat/mytools.py
chat/qa.py
chat/qa_sql.py
chat/semantic.py
chat/semantic2.py
chat/server.py
chat/sql.py
chat/tts.py
chat/word2pinyin.py
chat.egg-info/PKG-INFO
chat.egg-info/SOURCES.txt
chat.egg-info/dependency_links.txt
chat.egg-info/not-zip-safe
chat.egg-info/pbr.json
chat.egg-info/requires.txt
chat.egg-info/top_level.txt
chat/conf/self.conf
chat/data/answer.xml
chat/data/user.txt
chat/dict/sensitive_words.txt
chat/dict/stopwords.txt
chat/dict/swords.txt
chat/dict/synonymdict.txt
chat/dict/tagcount_1.pkl
chat/dict/tagcount_2.pkl
chat/dict/tagcount_3.pkl
chat/dict/tagcount_4.pkl
chat/dict/tagtree.pkl
chat/dict/userdict.txt
chat/dict/userdict_origin.txt
docs/Makefile
docs/make.bat
docs/build/doctrees/environment.pickle
docs/build/doctrees/index.doctree
docs/build/doctrees/modules/client.doctree
docs/build/doctrees/modules/mytools.doctree
docs/build/doctrees/modules/qa.doctree
docs/build/doctrees/modules/semantic.doctree
docs/build/doctrees/modules/server.doctree
docs/build/doctrees/user/architecture.doctree
docs/build/doctrees/user/custom.doctree
docs/build/doctrees/user/development.doctree
docs/build/doctrees/user/installation.doctree
docs/build/doctrees/user/thanks.doctree
docs/build/doctrees/user/tutorial.doctree
docs/build/html/.buildinfo
docs/build/html/.nojekyll
docs/build/html/genindex.html
docs/build/html/index.html
docs/build/html/objects.inv
docs/build/html/search.html
docs/build/html/searchindex.js
docs/build/html/_images/chat.png
docs/build/html/_images/mytools.ico
docs/build/html/_images/neo4j.png
docs/build/html/_images/qa.ico
docs/build/html/_images/semantic.ico
docs/build/html/_images/server.ico
docs/build/html/_modules/index.html
docs/build/html/_sources/index.txt
docs/build/html/_sources/modules/client.txt
docs/build/html/_sources/modules/mytools.txt
docs/build/html/_sources/modules/qa.txt
docs/build/html/_sources/modules/semantic.txt
docs/build/html/_sources/modules/server.txt
