Metadata-Version: 1.1
Name: chat
Version: 1.0.7.dev134
Summary: Chat robot based on natural language understanding and machine learning.
Home-page: http://pypi.python.org/pypi/chat
Author: Decalogue
Author-email: 1044908508@qq.com
License: MIT
Platform: UNKNOWN
Classifier: Development Status :: 5 - Production/Stable
Classifier: Environment :: Console
Classifier: Intended Audience :: Developers
Classifier: Intended Audience :: Information Technology
Classifier: Natural Language :: English
